node_py/__init__.py
node_py-0.0.25.dist-info/WHEEL
node_py-0.0.25.dist-info/METADATA
node_py-0.0.25.dist-info/RECORD
